biobeam/__init__.py
biobeam/version.py
biobeam/beam_gui/__init__.py
biobeam/beam_gui/beam_gui.py
biobeam/beam_gui/bpm3d_img.py
biobeam/beam_gui/fieldlistpanel.py
biobeam/beam_gui/fieldpanel.py
biobeam/beam_gui/fieldstate.py
biobeam/beam_gui/prop_panel.py
biobeam/beam_gui/volbeam.py
biobeam/core/__init__.py
biobeam/core/bpm3d.py
biobeam/core/focus_field_beam.py
biobeam/core/focus_field_cylindrical.py
biobeam/core/focus_field_lattice.py
biobeam/core/kernels/bessel.cl
biobeam/core/kernels/bpm_3d_kernels.cl
biobeam/core/kernels/psf_cylindrical.cl
biobeam/core/kernels/psf_debye.cl
biobeam/core/kernels/psf_lattice.cl
biobeam/data/__init__.py
biobeam/simlsm/__init__.py
biobeam/simlsm/sim_cylindrical.py
biobeam/simlsm/sim_dslm.py
biobeam/simlsm/sim_lattice.py
biobeam/simlsm/simlsm.py
biobeam/utils/__init__.py
biobeam/utils/bpm_cpu.py
biobeam/utils/oclmultireduction.py
biobeam/utils/ocloffsetreduction.py
biobeam/utils/reduction_test.py
biobeam/utils/utils.py
biobeam-0.1.3.dist-info/DESCRIPTION.rst
biobeam-0.1.3.dist-info/METADATA
biobeam-0.1.3.dist-info/RECORD
biobeam-0.1.3.dist-info/WHEEL
biobeam-0.1.3.dist-info/metadata.json
biobeam-0.1.3.dist-info/top_level.txt
