Metadata-Version: 2.0
Name: biobeam
Version: 0.1.3
Summary: GPU accelerated light propagation tools
Home-page: https://maweigert.github.io/biobeam
Author: Martin Weigert
Author-email: mweigert@mpi-cbg.de
License: MIT
Platform: UNKNOWN
Requires-Dist: numpy
Requires-Dist: scipy
Requires-Dist: pyopencl (>=2016.1)
Requires-Dist: gputools (>=0.1.3)
